grutils/__init__.py
grutils/configs.py
grutils/csv.py
grutils/easyform.py
grutils/error.py
grutils/excel.py
grutils/excel_manager.py
grutils/file.py
grutils/form.py
grutils/form_utils.py
grutils/formatter_and_parser.py
grutils/gui_event.py
grutils/iterable.py
grutils/logs_view_helper.py
grutils/printer.py
grutils/progress.py
grutils/tk_helper.py
grutils/utils.py
grutils/warnings_writer.py
grutils-0.1.11.21.dist-info/LICENSE
grutils-0.1.11.21.dist-info/METADATA
grutils-0.1.11.21.dist-info/WHEEL
grutils-0.1.11.21.dist-info/top_level.txt
grutils-0.1.11.21.dist-info/RECORD
