Metadata-Version: 2.1
Name: grutils
Version: 0.1.11.21
Summary: reusable grutils
Home-page: UNKNOWN
Author: leidong.liu
Author-email: leidong.liu@gmail.com
License: Apache2.0
Project-URL: Source, https://github.com/lldld/gr.py3.utils
Platform: UNKNOWN
Classifier: Topic :: Software Development :: Libraries
Classifier: Programming Language :: Python :: 3
Classifier: Programming Language :: Python :: 3.6
Requires-Python: >=3.6
Requires-Dist: xlwings ==0.18.0
Requires-Dist: chardet ==4.0.0
